pylint_ci/__init__.py
pylint_ci/__main__.py
pylint_ci/pylint_ci.py
pylint_ci-1.0.0.dist-info/DESCRIPTION.rst
pylint_ci-1.0.0.dist-info/METADATA
pylint_ci-1.0.0.dist-info/RECORD
pylint_ci-1.0.0.dist-info/WHEEL
pylint_ci-1.0.0.dist-info/entry_points.txt
pylint_ci-1.0.0.dist-info/metadata.json
pylint_ci-1.0.0.dist-info/top_level.txt
